setup.py
nae_inference/__init__.py
nae_inference.egg-info/PKG-INFO
nae_inference.egg-info/SOURCES.txt
nae_inference.egg-info/dependency_links.txt
nae_inference.egg-info/not-zip-safe
nae_inference.egg-info/top_level.txt