Metadata-Version: 1.0
Name: nae-inference
Version: 0.1
Summary: A dummy repo for nae-inference
Home-page: https://example.com/
Author: Flying Circus
Author-email: flyingcircus@example.com
License: MIT
Platform: UNKNOWN
